document_parse/__init__.py
document_parse/llamaparse.py
document_parse/main_file_s3_to_llamaparse.py
mcp_defect/__init__.py
mcp_defect/__main__.py
mcp_defect/constants.py
mcp_defect/databases.py
mcp_defect/generate_mail_html.py
mcp_defect/html_link_from_md.py
mcp_defect/prompts.py
mcp_defect/resources.py
mcp_defect/server.py
mcp_defect/tool_schema.py
mcp_defect/tools.py
mcp_defect/Agent/main.py
mcp_defect/Agent/markdown_logger.py
mcp_defect/Agent/setup.py
mcp_defect/Agent/app/__init__.py
mcp_defect/Agent/app/bedrock.py
mcp_defect/Agent/app/config.py
mcp_defect/Agent/app/exceptions.py
mcp_defect/Agent/app/llm.py
mcp_defect/Agent/app/logger.py
mcp_defect/Agent/app/schema.py
mcp_defect/Agent/app/toolHandler.py
mcp_defect/Agent/app/agent/__init__.py
mcp_defect/Agent/app/agent/base.py
mcp_defect/Agent/app/agent/casefileAgent.py
mcp_defect/Agent/app/agent/react.py
mcp_defect/Agent/app/agent/toolcall.py
mcp_defect/Agent/app/sandbox/__init__.py
mcp_defect/Agent/app/sandbox/client.py
mcp_defect/Agent/app/sandbox/core/exceptions.py
mcp_defect/Agent/app/sandbox/core/manager.py
mcp_defect/Agent/app/sandbox/core/sandbox.py
mcp_defect/Agent/app/sandbox/core/terminal.py
mcp_defect/Agent/app/tool/__init__.py
mcp_defect/Agent/app/tool/base.py
mcp_defect/Agent/app/tool/create_chat_completion.py
mcp_defect/Agent/app/tool/mcp_tool.py
mcp_defect/Agent/app/tool/terminate.py
mcp_defect/Agent/app/tool/tool_collection.py
mcp_defect/Agent/app/tool/search/__init__.py
mcp_defect/Agent/app/tool/search/baidu_search.py
mcp_defect/Agent/app/tool/search/base.py
mcp_defect/Agent/app/tool/search/bing_search.py
mcp_defect/Agent/app/tool/search/duckduckgo_search.py
mcp_defect/Agent/app/tool/search/google_search.py
mcp_defect/Agent/app/tool/search/vessel_database_search.py
mcp_defect/Agent/app/tool/search/vessel_search.py
mcp_defect/Agent/config/config.toml
mcp_defect/Agent/config/mcp_servers_config.json
mcp_defect/Agent/config/tools.json
mcp_defect/scheduler/executor.py
syia_mcp_defect_2025_x7k9-0.1.18.dist-info/METADATA
syia_mcp_defect_2025_x7k9-0.1.18.dist-info/WHEEL
syia_mcp_defect_2025_x7k9-0.1.18.dist-info/top_level.txt
syia_mcp_defect_2025_x7k9-0.1.18.dist-info/RECORD
